{"content": {"suites": {"0": {"status": {"total_pass": 1, "total_skip": 0, "total_xpass": 0, "total_xfail": 0, "total_rerun": 0, "total_fail": 0, "total_error": 0}, "tests": {"0": {"status": "PASS", "message": "", "test_name": "test_appt_reasons", "rerun": "0"}}, "suite_name": "tests/api/test_scheduling_api.py"}, "1": {"suite_name": "tests/web/test_login.py", "tests": {"0": {"status": "FAIL", "message": "       playwright._impl._errors.TimeoutError: Page.wait_for_selector: Timeout 30000ms exceeded.\n       Call log:\n       waiting for locator(\"//div/span/input[@id='okta-signin-username']\") to be visible\n", "test_name": "test_valid_login", "rerun": "0"}}, "status": {"total_pass": 0, "total_skip": 0, "total_xpass": 0, "total_xfail": 0, "total_rerun": 0, "total_fail": 1, "total_error": 0}}}}, "date": "August 13, 2024", "start_time": 1723592515.901355, "total_suite": 2, "status": "FAIL", "status_list": {"pass": "1", "fail": "1", "skip": "0", "error": "0", "xpass": "0", "xfail": "0", "rerun": "0"}, "total_tests": "2"}